[
    {
        "text": "FN",
        "left": 0,
        "top": 2587,
        "width": 54,
        "height": 8,
        "conf": 22
    },
    {
        "text": "PS",
        "left": 68,
        "top": 2588,
        "width": 57,
        "height": 7,
        "conf": 28
    },
    {
        "text": "Ty",
        "left": 177,
        "top": 2588,
        "width": 62,
        "height": 7,
        "conf": 18
    },
    {
        "text": "eee",
        "left": 254,
        "top": 2576,
        "width": 36,
        "height": 19,
        "conf": 38
    },
    {
        "text": "ee",
        "left": 297,
        "top": 2576,
        "width": 25,
        "height": 19,
        "conf": 15
    },
    {
        "text": "eee",
        "left": 345,
        "top": 2576,
        "width": 61,
        "height": 19,
        "conf": 21
    },
    {
        "text": "TO",
        "left": 424,
        "top": 2576,
        "width": 72,
        "height": 19,
        "conf": 32
    },
    {
        "text": "Oe",
        "left": 546,
        "top": 2576,
        "width": 53,
        "height": 19,
        "conf": 27
    },
    {
        "text": "Oe",
        "left": 622,
        "top": 2576,
        "width": 23,
        "height": 19,
        "conf": 38
    },
    {
        "text": "OE",
        "left": 652,
        "top": 2576,
        "width": 34,
        "height": 19,
        "conf": 9
    },
    {
        "text": "OS",
        "left": 714,
        "top": 2576,
        "width": 16,
        "height": 19,
        "conf": 11
    },
    {
        "text": "Pe",
        "left": 737,
        "top": 2576,
        "width": 19,
        "height": 19,
        "conf": 27
    },
    {
        "text": "ee",
        "left": 774,
        "top": 2576,
        "width": 32,
        "height": 19,
        "conf": 16
    },
    {
        "text": "rere",
        "left": 829,
        "top": 2576,
        "width": 50,
        "height": 19,
        "conf": 24
    }
]